jupyter_geppetto/__init__.py
jupyter_geppetto/handlers.py
jupyter_geppetto/index.js
jupyter_geppetto/service.py
jupyter_geppetto/settings.py
jupyter_geppetto/synchronization.py
jupyter_geppetto/utils.py
jupyter_geppetto/webapi.py
jupyter_geppetto/websocket_connection.py
jupyter_geppetto-1.1.5.data/data/share/jupyter/nbextensions/jupyter_geppetto/index.js
jupyter_geppetto-1.1.5.dist-info/LICENSE
jupyter_geppetto-1.1.5.dist-info/METADATA
jupyter_geppetto-1.1.5.dist-info/WHEEL
jupyter_geppetto-1.1.5.dist-info/top_level.txt
jupyter_geppetto-1.1.5.dist-info/RECORD
